supar/__init__.py
supar/cmds/__init__.py
supar/cmds/biaffine_dep.py
supar/cmds/biaffine_sdp.py
supar/cmds/cmd.py
supar/cmds/crf2o_dep.py
supar/cmds/crf_con.py
supar/cmds/crf_dep.py
supar/cmds/vi_con.py
supar/cmds/vi_dep.py
supar/cmds/vi_sdp.py
supar/models/__init__.py
supar/models/const.py
supar/models/dep.py
supar/models/model.py
supar/models/sdp.py
supar/modules/__init__.py
supar/modules/affine.py
supar/modules/dropout.py
supar/modules/lstm.py
supar/modules/mlp.py
supar/modules/pretrained.py
supar/modules/scalar_mix.py
supar/modules/transformer.py
supar/parsers/__init__.py
supar/parsers/const.py
supar/parsers/dep.py
supar/parsers/parser.py
supar/parsers/sdp.py
supar/structs/__init__.py
supar/structs/dist.py
supar/structs/fn.py
supar/structs/linearchain.py
supar/structs/semiring.py
supar/structs/tree.py
supar/structs/vi.py
supar/utils/__init__.py
supar/utils/common.py
supar/utils/config.py
supar/utils/data.py
supar/utils/embedding.py
supar/utils/field.py
supar/utils/fn.py
supar/utils/logging.py
supar/utils/metric.py
supar/utils/parallel.py
supar/utils/tokenizer.py
supar/utils/transform.py
supar/utils/vocab.py
supar-1.1.4.dist-info/LICENSE
supar-1.1.4.dist-info/METADATA
supar-1.1.4.dist-info/WHEEL
supar-1.1.4.dist-info/entry_points.txt
supar-1.1.4.dist-info/top_level.txt
supar-1.1.4.dist-info/RECORD
