Metadata-Version: 2.1
Name: supar
Version: 1.1.4
Summary: Syntactic/Semantic Parsing Models
Home-page: https://github.com/yzhangcs/parser
Author: Yu Zhang
Author-email: yzhang.cs@outlook.com
License: UNKNOWN
Platform: UNKNOWN
Classifier: Programming Language :: Python :: 3
Classifier: License :: OSI Approved :: MIT License
Classifier: Operating System :: OS Independent
Classifier: Topic :: Scientific/Engineering :: Artificial Intelligence
Classifier: Topic :: Text Processing :: Linguistic
Requires-Python: >=3.7
Requires-Dist: torch (>=1.7.1)
Requires-Dist: transformers (>=4.0.0)
Requires-Dist: nltk
Requires-Dist: stanza
Requires-Dist: dill
Requires-Dist: numpy (<1.21.5) ; python_version < "3.8"
Provides-Extra: elmo
Requires-Dist: allennlp ; extra == 'elmo'
